ert_storage/__init__.py
ert_storage/__main__.py
ert_storage/app.py
ert_storage/database.py
ert_storage/exceptions.py
ert_storage/py.typed
ert_storage/security.py
ert_storage/_alembic/alembic.ini
ert_storage/_alembic/alembic/env.py
ert_storage/_alembic/alembic/versions/021d7514e351_add_recordinfo.py
ert_storage/_alembic/alembic/versions/057555237953_make_metadata_not_nullable.py
ert_storage/_alembic/alembic/versions/1a4a83dfb895_add_metadata_column.py
ert_storage/_alembic/alembic/versions/4effed76d1e2_inline_parameters_into_ensembles.py
ert_storage/_alembic/alembic/versions/55307b70da13_add_record_class.py
ert_storage/_alembic/alembic/versions/56177419dc39_add_priors.py
ert_storage/_alembic/alembic/versions/65569f4f3756_add_name_to_record.py
ert_storage/_alembic/alembic/versions/73541c7b7aa6_add_size_to_ensemble.py
ert_storage/_alembic/alembic/versions/7812741cc469_recordtype_as_enum.py
ert_storage/_alembic/alembic/versions/79137bad215d_add_matrix_labels.py
ert_storage/_alembic/alembic/versions/896a28a0652f_add_file_block.py
ert_storage/_alembic/alembic/versions/9064db29af73_record_as_inputs_and_outputs_of_.py
ert_storage/_alembic/alembic/versions/98601344bcf5_add_realization_index_to_record.py
ert_storage/_alembic/alembic/versions/9a218c7df2ac_separate_into_file_matrix.py
ert_storage/_alembic/alembic/versions/a3f7ae51a72b_initial_schema.py
ert_storage/_alembic/alembic/versions/a88924af33b0_add_experiment.py
ert_storage/_alembic/alembic/versions/abccdeea2826_add_active_realizations_to_ensemble.py
ert_storage/_alembic/alembic/versions/ba7905904381_add_backend_agnostic_uuid_type.py
ert_storage/_alembic/alembic/versions/bea15008ea91_add_obs_trans_and_updates.py
ert_storage/_alembic/alembic/versions/c1b95721c62a_add_azure_blob_storage.py
ert_storage/_alembic/alembic/versions/c96ec073f9ee_change_prior_enum.py
ert_storage/_alembic/alembic/versions/d72e51c6bdf2_remove_record_class.py
ert_storage/_alembic/alembic/versions/f46d5afa7639_add_observations.py
ert_storage-0.3.22.dist-info/LICENSE
ert_storage-0.3.22.dist-info/METADATA
ert_storage-0.3.22.dist-info/WHEEL
ert_storage-0.3.22.dist-info/entry_points.txt
ert_storage-0.3.22.dist-info/top_level.txt
ert_storage-0.3.22.dist-info/RECORD
