Metadata-Version: 2.1
Name: ert-storage
Version: 0.3.22
Summary: Storage service for ERT
Home-page: https://github.com/equinor/ert-storage
Author: Equinor ASA
Author-email: fg_sib-scout@equinor.com
License: GPLv3
License-File: LICENSE
Requires-Dist: alembic
Requires-Dist: fastapi (<0.100.0)
Requires-Dist: httpx
Requires-Dist: numpy
Requires-Dist: pandas
Requires-Dist: pyarrow
Requires-Dist: pydantic (<2)
Requires-Dist: python-multipart
Requires-Dist: requests
Requires-Dist: sqlalchemy (>=1.4)
Requires-Dist: uvicorn (>=0.17.0)
Provides-Extra: azure
Requires-Dist: aiohttp ; extra == 'azure'
Requires-Dist: azure-storage-blob ; extra == 'azure'
Provides-Extra: postgres
Requires-Dist: psycopg2 ; extra == 'postgres'
Provides-Extra: test
Requires-Dist: black ; extra == 'test'
Requires-Dist: pytest ; extra == 'test'
Requires-Dist: pytest-asyncio ; extra == 'test'
Requires-Dist: mypy (==0.981) ; extra == 'test'
Requires-Dist: types-requests ; extra == 'test'
